<package>
  <description>A ROS node that uses the Player libwavefront_standalone library, which implements wavefront path-planning for a planar robot.</description>
  <author>Brian P. Gerkey</author>
  <license>BSD</license>
  <review status="unreviewed" notes=""/>
  <depend package="roscpp" />
  <depend package="player" />
  <depend package="laser_scan" />
  <depend package="std_srvs" />
  <depend package="robot_msgs" />
  <depend package="tf"/>
  <export>
    <cpp cflags="-I${prefix}/srv/cpp"/>
  </export>
</package>
