<launch>
  <master auto="start"/>
  <group name="wg">

    <!-- startup Gazebo with robot and default mechanism controllers -->
    <include file="$(find pr2_gazebo)/pr2_obs.launch"/>

    <node pkg="map_server" type="map_server" args="$(find gazebo_robot_description)/world/Media/materials/textures/map3.png 0.1" respawn="false" />

    <node pkg="amcl_player" type="amcl_player" args="scan:=base_scan" respawn="false" />

    <include file="$(find world_3d_map)/run.xml"/>

    <node pkg="kinematic_planning" type="kinematic_planning" args="robotdesc/pr2"/>

    <node pkg="wavefront_player" type="wavefront_player" args="" respawn="false" />

    <node pkg="highlevel_controllers" type="move_arm" args="right" respawn="false"/>

<!-- Until we resolve mechanism state issue - comment out other arm
    <node pkg="highlevel_controllers" type="move_arm" args="left" respawn="false" />
-->

    <node pkg="nav_view" type="nav_view" respawn="false" />
  </group>
</launch>
