<package>
  <description brief="A node to use the sbpl arm planner for the PR2 arm">
    
  </description>
  <author>Sachin Chitta /sachinc@willowgarage.com</author>
  <license>BSD</license>
    <depend package="roscpp"/>
    <depend package="std_msgs"/>
    <depend package="robot_msgs" />
    <depend package="sbpl_arm_planner" />
    <depend package="tf" />
  <url></url>
  
  <export>
      <cpp cflags="-I${prefix}/include -I${prefix}/srv/cpp -O3 -g" lflags="-Wl, -rpath,${prefix}/lib -L${prefix}/lib"/>
  </export>
  
</package>

