<stack name="simulators" version="0.1">
  <description brief="Stage and Gazebo Simulators">
    Simulators for ROS both Stage and Gazebo
  </description>
  <author>John Hsu johnhsu@willowgarage.com</author>
  <license>BSD</license>
  <review status="unreviewed" notes=""/>
  <url>http://pr.willowgarage.com/wiki/simulators</url>
  

  <depend stack="geometry"/> <!-- bullet, tf --> 
  <depend stack="ros"/> <!-- roscpp, std_msgs --> 
  <depend stack="visualization_common"/> <!-- ogre --> 
  <depend stack="common_msgs"/> <!-- sensor_msgs --> 

</stack>
